tablemodel/__init__.py
tablemodel/tablemodel.py
tablemodel-0.0.1.dist-info/LICENSE
tablemodel-0.0.1.dist-info/METADATA
tablemodel-0.0.1.dist-info/WHEEL
tablemodel-0.0.1.dist-info/top_level.txt
tablemodel-0.0.1.dist-info/RECORD
